Workbook

Sheet Raw Data
A1: Ride ID | B1: Date | C1: Pickup Location | D1: Drop-off Location | E1: Fare | F1: Payment Method | G1: Ride Status | H1: Rating | I1: Weekday | J1: Week No. | K1: Route | L1: Fare Tier
A2: R001 | B2: 46255 | C2: Gulberg | D2: DHA | E2: 713 | F2: Cash | G2: Completed | H2: 5 | I2: =TEXT(B2,"dddd") -> Friday | J2: =WEEKNUM(B2,2) -> 34 | K2: =C2&" -> "&D2 -> Gulberg -> DHA | L2: =IF(E2<Params!$B$5,"Low",IF(E2<=Params!$B$6,"Mid","High")) -> Mid
A3: R002 | B3: 46238 | C3: Gulberg | D3: Askari | E3: 215 | F3: Cash | G3: Completed | H3: 3 | I3: =TEXT(B3,"dddd") -> Tuesday | J3: =WEEKNUM(B3,2) -> 32 | K3: =C3&" -> "&D3 -> Gulberg -> Askari | L3: =IF(E3<Params!$B$5,"Low",IF(E3<=Params!$B$6,"Mid","High")) -> Low
A4: R003 | B4: 46251 | C4: Lahore | D4: Cantt | E4: 1009 | F4: Cash | G4: Completed | H4: 4 | I4: =TEXT(B4,"dddd") -> Monday | J4: =WEEKNUM(B4,2) -> 34 | K4: =C4&" -> "&D4 -> Lahore -> Cantt | L4: =IF(E4<Params!$B$5,"Low",IF(E4<=Params!$B$6,"Mid","High")) -> High
A5: R004 | B5: 46260 | C5: Lahore | D5: Model Town | E5: 1015 | F5: Card | G5: Completed | H5: 3 | I5: =TEXT(B5,"dddd") -> Wednesday | J5: =WEEKNUM(B5,2) -> 35 | K5: =C5&" -> "&D5 -> Lahore -> Model Town | L5: =IF(E5<Params!$B$5,"Low",IF(E5<=Params!$B$6,"Mid","High")) -> High
A6: R005 | B6: 46259 | C6: Bahria Town | D6: Gulberg | E6: 339 | F6: Card | G6: Completed | H6: 4 | I6: =TEXT(B6,"dddd") -> Tuesday | J6: =WEEKNUM(B6,2) -> 35 | K6: =C6&" -> "&D6 -> Bahria Town -> Gulberg | L6: =IF(E6<Params!$B$5,"Low",IF(E6<=Params!$B$6,"Mid","High")) -> Low
A7: R006 | B7: 46254 | C7: Johar Town | D7: DHA | E7: 1090 | F7: Wallet | G7: Completed | H7: 4 | I7: =TEXT(B7,"dddd") -> Thursday | J7: =WEEKNUM(B7,2) -> 34 | K7: =C7&" -> "&D7 -> Johar Town -> DHA | L7: =IF(E7<Params!$B$5,"Low",IF(E7<=Params!$B$6,"Mid","High")) -> High
A8: R007 | B8: 46237 | C8: Johar Town | D8: Faisal Town | E8: 543 | F8: Wallet | G8: Completed | H8: 5 | I8: =TEXT(B8,"dddd") -> Monday | J8: =WEEKNUM(B8,2) -> 32 | K8: =C8&" -> "&D8 -> Johar Town -> Faisal Town | L8: =IF(E8<Params!$B$5,"Low",IF(E8<=Params!$B$6,"Mid","High")) -> Low
A9: R008 | B9: 46242 | C9: Johar Town | D9: Gulberg | E9: 626 | F9: Cash | G9: Completed | H9: 4 | I9: =TEXT(B9,"dddd") -> Saturday | J9: =WEEKNUM(B9,2) -> 32 | K9: =C9&" -> "&D9 -> Johar Town -> Gulberg | L9: =IF(E9<Params!$B$5,"Low",IF(E9<=Params!$B$6,"Mid","High")) -> Mid
A10: R009 | B10: 46255 | C10: Bahria Town | D10: Model Town | E10: 908 | F10: Card | G10: Completed | H10: 4 | I10: =TEXT(B10,"dddd") -> Friday | J10: =WEEKNUM(B10,2) -> 34 | K10: =C10&" -> "&D10 -> Bahria Town -> Model Town | L10: =IF(E10<Params!$B$5,"Low",IF(E10<=Params!$B$6,"Mid","High")) -> High
A11: R010 | B11: 46257 | C11: Gulberg | D11: Model Town | E11: 651 | F11: Cash | G11: Completed | H11: 4 | I11: =TEXT(B11,"dddd") -> Sunday | J11: =WEEKNUM(B11,2) -> 34 | K11: =C11&" -> "&D11 -> Gulberg -> Model Town | L11: =IF(E11<Params!$B$5,"Low",IF(E11<=Params!$B$6,"Mid","High")) -> Mid
A12: R011 | B12: 46264 | C12: Model Town | D12: Faisal Town | E12: 264 | F12: Cash | G12: Cancelled | I12: =TEXT(B12,"dddd") -> Sunday | J12: =WEEKNUM(B12,2) -> 35 | K12: =C12&" -> "&D12 -> Model Town -> Faisal Town | L12: =IF(E12<Params!$B$5,"Low",IF(E12<=Params!$B$6,"Mid","High")) -> Low
A13: R012 | B13: 46260 | C13: Bahria Town | D13: Askari | E13: 698 | F13: Cash | G13: Completed | H13: 5 | I13: =TEXT(B13,"dddd") -> Wednesday | J13: =WEEKNUM(B13,2) -> 35 | K13: =C13&" -> "&D13 -> Bahria Town -> Askari | L13: =IF(E13<Params!$B$5,"Low",IF(E13<=Params!$B$6,"Mid","High")) -> Mid
A14: R013 | B14: 46263 | C14: Bahria Town | D14: Cantt | E14: 1172 | F14: Card | G14: Cancelled | I14: =TEXT(B14,"dddd") -> Saturday | J14: =WEEKNUM(B14,2) -> 35 | K14: =C14&" -> "&D14 -> Bahria Town -> Cantt | L14: =IF(E14<Params!$B$5,"Low",IF(E14<=Params!$B$6,"Mid","High")) -> High
A15: R014 | B15: 46255 | C15: Iqbal Town | D15: Model Town | E15: 692 | F15: Cash | G15: Completed | H15: 5 | I15: =TEXT(B15,"dddd") -> Friday | J15: =WEEKNUM(B15,2) -> 34 | K15: =C15&" -> "&D15 -> Iqbal Town -> Model Town | L15: =IF(E15<Params!$B$5,"Low",IF(E15<=Params!$B$6,"Mid","High")) -> Mid
A16: R015 | B16: 46252 | C16: Johar Town | D16: Askari | E16: 967 | F16: Card | G16: Completed | H16: 3 | I16: =TEXT(B16,"dddd") -> Tuesday | J16: =WEEKNUM(B16,2) -> 34 | K16: =C16&" -> "&D16 -> Johar Town -> Askari | L16: =IF(E16<Params!$B$5,"Low",IF(E16<=Params!$B$6,"Mid","High")) -> High
A17: R016 | B17: 46251 | C17: Iqbal Town | D17: Gulberg | E17: 246 | F17: Cash | G17: Completed | H17: 3 | I17: =TEXT(B17,"dddd") -> Monday | J17: =WEEKNUM(B17,2) -> 34 | K17: =C17&" -> "&D17 -> Iqbal Town -> Gulberg | L17: =IF(E17<Params!$B$5,"Low",IF(E17<=Params!$B$6,"Mid","High")) -> Low
A18: R017 | B18: 46260 | C18: Wapda Town | D18: Gulberg | E18: 938 | F18: Card | G18: Completed | H18: 4 | I18: =TEXT(B18,"dddd") -> Wednesday | J18: =WEEKNUM(B18,2) -> 35 | K18: =C18&" -> "&D18 -> Wapda Town -> Gulberg | L18: =IF(E18<Params!$B$5,"Low",IF(E18<=Params!$B$6,"Mid","High")) -> High
A19: R018 | B19: 46251 | C19: Johar Town | D19: DHA | E19: 384 | F19: Wallet | G19: Cancelled | I19: =TEXT(B19,"dddd") -> Monday | J19: =WEEKNUM(B19,2) -> 34 | K19: =C19&" -> "&D19 -> Johar Town -> DHA | L19: =IF(E19<Params!$B$5,"Low",IF(E19<=Params!$B$6,"Mid","High")) -> Low
A20: R019 | B20: 46259 | C20: Johar Town | D20: Faisal Town | E20: 378 | F20: Card | G20: Completed | H20: 4 | I20: =TEXT(B20,"dddd") -> Tuesday | J20: =WEEKNUM(B20,2) -> 35 | K20: =C20&" -> "&D20 -> Johar Town -> Faisal Town | L20: =IF(E20<Params!$B$5,"Low",IF(E20<=Params!$B$6,"Mid","High")) -> Low
A21: R020 | B21: 46235 | C21: Johar Town | D21: Model Town | E21: 1189 | F21: Cash | G21: Cancelled | I21: =TEXT(B21,"dddd") -> Saturday | J21: =WEEKNUM(B21,2) -> 31 | K21: =C21&" -> "&D21 -> Johar Town -> Model Town | L21: =IF(E21<Params!$B$5,"Low",IF(E21<=Params!$B$6,"Mid","High")) -> High
A22: R021 | B22: 46244 | C22: Model Town | D22: Model Town | E22: 915 | F22: Cash | G22: Completed | H22: 5 | I22: =TEXT(B22,"dddd") -> Monday | J22: =WEEKNUM(B22,2) -> 33 | K22: =C22&" -> "&D22 -> Model Town -> Model Town | L22: =IF(E22<Params!$B$5,"Low",IF(E22<=Params!$B$6,"Mid","High")) -> High
A23: R022 | B23: 46264 | C23: Lahore | D23: Faisal Town | E23: 1150 | F23: Cash | G23: Completed | H23: 4 | I23: =TEXT(B23,"dddd") -> Sunday | J23: =WEEKNUM(B23,2) -> 35 | K23: =C23&" -> "&D23 -> Lahore -> Faisal Town | L23: =IF(E23<Params!$B$5,"Low",IF(E23<=Params!$B$6,"Mid","High")) -> High
A24: R023 | B24: 46263 | C24: Johar Town | D24: Cantt | E24: 268 | F24: Cash | G24: Cancelled | I24: =TEXT(B24,"dddd") -> Saturday | J24: =WEEKNUM(B24,2) -> 35 | K24: =C24&" -> "&D24 -> Johar Town -> Cantt | L24: =IF(E24<Params!$B$5,"Low",IF(E24<=Params!$B$6,"Mid","High")) -> Low
A25: R024 | B25: 46237 | C25: Gulberg | D25: Airport | E25: 291 | F25: Wallet | G25: Completed | H25: 3 | I25: =TEXT(B25,"dddd") -> Monday | J25: =WEEKNUM(B25,2) -> 32 | K25: =C25&" -> "&D25 -> Gulberg -> Airport | L25: =IF(E25<Params!$B$5,"Low",IF(E25<=Params!$B$6,"Mid","High")) -> Low
A26: R025 | B26: 46256 | C26: Iqbal Town | D26: Model Town | E26: 692 | F26: Wallet | G26: Cancelled | I26: =TEXT(B26,"dddd") -> Saturday | J26: =WEEKNUM(B26,2) -> 34 | K26: =C26&" -> "&D26 -> Iqbal Town -> Model Town | L26: =IF(E26<Params!$B$5,"Low",IF(E26<=Params!$B$6,"Mid","High")) -> Mid
A27: R026 | B27: 46248 | C27: Model Town | D27: Cantt | E27: 788 | F27: Card | G27: Cancelled | I27: =TEXT(B27,"dddd") -> Friday | J27: =WEEKNUM(B27,2) -> 33 | K27: =C27&" -> "&D27 -> Model Town -> Cantt | L27: =IF(E27<Params!$B$5,"Low",IF(E27<=Params!$B$6,"Mid","High")) -> Mid
A28: R027 | B28: 46255 | C28: Bahria Town | D28: Airport | E28: 1074 | F28: Cash | G28: Completed | H28: 3 | I28: =TEXT(B28,"dddd") -> Friday | J28: =WEEKNUM(B28,2) -> 34 | K28: =C28&" -> "&D28 -> Bahria Town -> Airport | L28: =IF(E28<Params!$B$5,"Low",IF(E28<=Params!$B$6,"Mid","High")) -> High
A29: R028 | B29: 46245 | C29: Lahore | D29: Cantt | E29: 601 | F29: Cash | G29: Completed | H29: 5 | I29: =TEXT(B29,"dddd") -> Tuesday | J29: =WEEKNUM(B29,2) -> 33 | K29: =C29&" -> "&D29 -> Lahore -> Cantt | L29: =IF(E29<Params!$B$5,"Low",IF(E29<=Params!$B$6,"Mid","High")) -> Mid
A30: R029 | B30: 46236 | C30: Model Town | D30: Gulberg | E30: 214 | F30: Card | G30: Completed | H30: 3 | I30: =TEXT(B30,"dddd") -> Sunday | J30: =WEEKNUM(B30,2) -> 31 | K30: =C30&" -> "&D30 -> Model Town -> Gulberg | L30: =IF(E30<Params!$B$5,"Low",IF(E30<=Params!$B$6,"Mid","High")) -> Low
A31: R030 | B31: 46243 | C31: Iqbal Town | D31: Cantt | E31: 420 | F31: Wallet | G31: Cancelled | I31: =TEXT(B31,"dddd") -> Sunday | J31: =WEEKNUM(B31,2) -> 32 | K31: =C31&" -> "&D31 -> Iqbal Town -> Cantt | L31: =IF(E31<Params!$B$5,"Low",IF(E31<=Params!$B$6,"Mid","High")) -> Low
A32: R031 | B32: 46253 | C32: Iqbal Town | D32: Cantt | E32: 1118 | F32: Card | G32: Completed | H32: 3 | I32: =TEXT(B32,"dddd") -> Wednesday | J32: =WEEKNUM(B32,2) -> 34 | K32: =C32&" -> "&D32 -> Iqbal Town -> Cantt | L32: =IF(E32<Params!$B$5,"Low",IF(E32<=Params!$B$6,"Mid","High")) -> High
A33: R032 | B33: 46256 | C33: Wapda Town | D33: Faisal Town | E33: 1017 | F33: Card | G33: Completed | H33: 5 | I33: =TEXT(B33,"dddd") -> Saturday | J33: =WEEKNUM(B33,2) -> 34 | K33: =C33&" -> "&D33 -> Wapda Town -> Faisal Town | L33: =IF(E33<Params!$B$5,"Low",IF(E33<=Params!$B$6,"Mid","High")) -> High
A34: R033 | B34: 46236 | C34: Gulberg | D34: DHA | E34: 974 | F34: Wallet | G34: Completed | H34: 3 | I34: =TEXT(B34,"dddd") -> Sunday | J34: =WEEKNUM(B34,2) -> 31 | K34: =C34&" -> "&D34 -> Gulberg -> DHA | L34: =IF(E34<Params!$B$5,"Low",IF(E34<=Params!$B$6,"Mid","High")) -> High
A35: R034 | B35: 46242 | C35: Model Town | D35: Cantt | E35: 1068 | F35: Cash | G35: Completed | H35: 4 | I35: =TEXT(B35,"dddd") -> Saturday | J35: =WEEKNUM(B35,2) -> 32 | K35: =C35&" -> "&D35 -> Model Town -> Cantt | L35: =IF(E35<Params!$B$5,"Low",IF(E35<=Params!$B$6,"Mid","High")) -> High
A36: R035 | B36: 46249 | C36: Model Town | D36: Gulberg | E36: 1057 | F36: Wallet | G36: Completed | H36: 5 | I36: =TEXT(B36,"dddd") -> Saturday | J36: =WEEKNUM(B36,2) -> 33 | K36: =C36&" -> "&D36 -> Model Town -> Gulberg | L36: =IF(E36<Params!$B$5,"Low",IF(E36<=Params!$B$6,"Mid","High")) -> High
A37: R036 | B37: 46252 | C37: Lahore | D37: Gulberg | E37: 634 | F37: Cash | G37: Completed | H37: 4 | I37: =TEXT(B37,"dddd") -> Tuesday | J37: =WEEKNUM(B37,2) -> 34 | K37: =C37&" -> "&D37 -> Lahore -> Gulberg | L37: =IF(E37<Params!$B$5,"Low",IF(E37<=Params!$B$6,"Mid","High")) -> Mid
A38: R037 | B38: 46241 | C38: Wapda Town | D38: DHA | E38: 487 | F38: Card | G38: Completed | H38: 4 | I38: =TEXT(B38,"dddd") -> Friday | J38: =WEEKNUM(B38,2) -> 32 | K38: =C38&" -> "&D38 -> Wapda Town -> DHA | L38: =IF(E38<Params!$B$5,"Low",IF(E38<=Params!$B$6,"Mid","High")) -> Low
A39: R038 | B39: 46243 | C39: Iqbal Town | D39: Township | E39: 1016 | F39: Wallet | G39: Cancelled | I39: =TEXT(B39,"dddd") -> Sunday | J39: =WEEKNUM(B39,2) -> 32 | K39: =C39&" -> "&D39 -> Iqbal Town -> Township | L39: =IF(E39<Params!$B$5,"Low",IF(E39<=Params!$B$6,"Mid","High")) -> High
A40: R039 | B40: 46260 | C40: Iqbal Town | D40: Model Town | E40: 538 | F40: Card | G40: Completed | H40: 3 | I40: =TEXT(B40,"dddd") -> Wednesday | J40: =WEEKNUM(B40,2) -> 35 | K40: =C40&" -> "&D40 -> Iqbal Town -> Model Town | L40: =IF(E40<Params!$B$5,"Low",IF(E40<=Params!$B$6,"Mid","High")) -> Low
A41: R040 | B41: 46253 | C41: Lahore | D41: Faisal Town | E41: 267 | F41: Cash | G41: Completed | H41: 5 | I41: =TEXT(B41,"dddd") -> Wednesday | J41: =WEEKNUM(B41,2) -> 34 | K41: =C41&" -> "&D41 -> Lahore -> Faisal Town | L41: =IF(E41<Params!$B$5,"Low",IF(E41<=Params!$B$6,"Mid","High")) -> Low
A42: R041 | B42: 46264 | C42: DHA | D42: DHA | E42: 1190 | F42: Cash | G42: Cancelled | I42: =TEXT(B42,"dddd") -> Sunday | J42: =WEEKNUM(B42,2) -> 35 | K42: =C42&" -> "&D42 -> DHA -> DHA | L42: =IF(E42<Params!$B$5,"Low",IF(E42<=Params!$B$6,"Mid","High")) -> High
A43: R042 | B43: 46237 | C43: Gulberg | D43: Cantt | E43: 976 | F43: Cash | G43: Cancelled | I43: =TEXT(B43,"dddd") -> Monday | J43: =WEEKNUM(B43,2) -> 32 | K43: =C43&" -> "&D43 -> Gulberg -> Cantt | L43: =IF(E43<Params!$B$5,"Low",IF(E43<=Params!$B$6,"Mid","High")) -> High
A44: R043 | B44: 46253 | C44: Model Town | D44: DHA | E44: 317 | F44: Card | G44: Completed | H44: 5 | I44: =TEXT(B44,"dddd") -> Wednesday | J44: =WEEKNUM(B44,2) -> 34 | K44: =C44&" -> "&D44 -> Model Town -> DHA | L44: =IF(E44<Params!$B$5,"Low",IF(E44<=Params!$B$6,"Mid","High")) -> Low
A45: R044 | B45: 46251 | C45: Bahria Town | D45: Township | E45: 568 | F45: Wallet | G45: Completed | H45: 3 | I45: =TEXT(B45,"dddd") -> Monday | J45: =WEEKNUM(B45,2) -> 34 | K45: =C45&" -> "&D45 -> Bahria Town -> Township | L45: =IF(E45<Params!$B$5,"Low",IF(E45<=Params!$B$6,"Mid","High")) -> Mid
A46: R045 | B46: 46243 | C46: Wapda Town | D46: Model Town | E46: 764 | F46: Card | G46: Completed | H46: 3 | I46: =TEXT(B46,"dddd") -> Sunday | J46: =WEEKNUM(B46,2) -> 32 | K46: =C46&" -> "&D46 -> Wapda Town -> Model Town | L46: =IF(E46<Params!$B$5,"Low",IF(E46<=Params!$B$6,"Mid","High")) -> Mid
A47: R046 | B47: 46235 | C47: Iqbal Town | D47: Gulberg | E47: 300 | F47: Wallet | G47: Completed | H47: 4 | I47: =TEXT(B47,"dddd") -> Saturday | J47: =WEEKNUM(B47,2) -> 31 | K47: =C47&" -> "&D47 -> Iqbal Town -> Gulberg | L47: =IF(E47<Params!$B$5,"Low",IF(E47<=Params!$B$6,"Mid","High")) -> Low
A48: R047 | B48: 46239 | C48: Bahria Town | D48: Gulberg | E48: 650 | F48: Card | G48: Completed | H48: 4 | I48: =TEXT(B48,"dddd") -> Wednesday | J48: =WEEKNUM(B48,2) -> 32 | K48: =C48&" -> "&D48 -> Bahria Town -> Gulberg | L48: =IF(E48<Params!$B$5,"Low",IF(E48<=Params!$B$6,"Mid","High")) -> Mid
A49: R048 | B49: 46261 | C49: Johar Town | D49: DHA | E49: 763 | F49: Wallet | G49: Completed | H49: 3 | I49: =TEXT(B49,"dddd") -> Thursday | J49: =WEEKNUM(B49,2) -> 35 | K49: =C49&" -> "&D49 -> Johar Town -> DHA | L49: =IF(E49<Params!$B$5,"Low",IF(E49<=Params!$B$6,"Mid","High")) -> Mid
A50: R049 | B50: 46243 | C50: Gulberg | D50: Gulberg | E50: 468 | F50: Card | G50: Completed | H50: 3 | I50: =TEXT(B50,"dddd") -> Sunday | J50: =WEEKNUM(B50,2) -> 32 | K50: =C50&" -> "&D50 -> Gulberg -> Gulberg | L50: =IF(E50<Params!$B$5,"Low",IF(E50<=Params!$B$6,"Mid","High")) -> Low
A51: R050 | B51: 46257 | C51: Bahria Town | D51: Cantt | E51: 690 | F51: Wallet | G51: Completed | H51: 3 | I51: =TEXT(B51,"dddd") -> Sunday | J51: =WEEKNUM(B51,2) -> 34 | K51: =C51&" -> "&D51 -> Bahria Town -> Cantt | L51: =IF(E51<Params!$B$5,"Low",IF(E51<=Params!$B$6,"Mid","High")) -> Mid
A52: R051 | B52: 46237 | C52: Wapda Town | D52: Township | E52: 240 | F52: Cash | G52: Completed | H52: 3 | I52: =TEXT(B52,"dddd") -> Monday | J52: =WEEKNUM(B52,2) -> 32 | K52: =C52&" -> "&D52 -> Wapda Town -> Township | L52: =IF(E52<Params!$B$5,"Low",IF(E52<=Params!$B$6,"Mid","High")) -> Low
A53: R052 | B53: 46255 | C53: Johar Town | D53: Model Town | E53: 1054 | F53: Wallet | G53: Completed | H53: 5 | I53: =TEXT(B53,"dddd") -> Friday | J53: =WEEKNUM(B53,2) -> 34 | K53: =C53&" -> "&D53 -> Johar Town -> Model Town | L53: =IF(E53<Params!$B$5,"Low",IF(E53<=Params!$B$6,"Mid","High")) -> High
A54: R053 | B54: 46235 | C54: Gulberg | D54: Gulberg | E54: 455 | F54: Wallet | G54: Completed | H54: 4 | I54: =TEXT(B54,"dddd") -> Saturday | J54: =WEEKNUM(B54,2) -> 31 | K54: =C54&" -> "&D54 -> Gulberg -> Gulberg | L54: =IF(E54<Params!$B$5,"Low",IF(E54<=Params!$B$6,"Mid","High")) -> Low
A55: R054 | B55: 46253 | C55: DHA | D55: Askari | E55: 411 | F55: Cash | G55: Completed | H55: 3 | I55: =TEXT(B55,"dddd") -> Wednesday | J55: =WEEKNUM(B55,2) -> 34 | K55: =C55&" -> "&D55 -> DHA -> Askari | L55: =IF(E55<Params!$B$5,"Low",IF(E55<=Params!$B$6,"Mid","High")) -> Low
A56: R055 | B56: 46263 | C56: Bahria Town | D56: Cantt | E56: 661 | F56: Wallet | G56: Completed | H56: 5 | I56: =TEXT(B56,"dddd") -> Saturday | J56: =WEEKNUM(B56,2) -> 35 | K56: =C56&" -> "&D56 -> Bahria Town -> Cantt | L56: =IF(E56<Params!$B$5,"Low",IF(E56<=Params!$B$6,"Mid","High")) -> Mid
A57: R056 | B57: 46263 | C57: Wapda Town | D57: Model Town | E57: 634 | F57: Cash | G57: Cancelled | I57: =TEXT(B57,"dddd") -> Saturday | J57: =WEEKNUM(B57,2) -> 35 | K57: =C57&" -> "&D57 -> Wapda Town -> Model Town | L57: =IF(E57<Params!$B$5,"Low",IF(E57<=Params!$B$6,"Mid","High")) -> Mid
A58: R057 | B58: 46260 | C58: DHA | D58: Askari | E58: 200 | F58: Cash | G58: Completed | H58: 4 | I58: =TEXT(B58,"dddd") -> Wednesday | J58: =WEEKNUM(B58,2) -> 35 | K58: =C58&" -> "&D58 -> DHA -> Askari | L58: =IF(E58<Params!$B$5,"Low",IF(E58<=Params!$B$6,"Mid","High")) -> Low
A59: R058 | B59: 46260 | C59: Wapda Town | D59: Cantt | E59: 696 | F59: Cash | G59: Completed | H59: 3 | I59: =TEXT(B59,"dddd") -> Wednesday | J59: =WEEKNUM(B59,2) -> 35 | K59: =C59&" -> "&D59 -> Wapda Town -> Cantt | L59: =IF(E59<Params!$B$5,"Low",IF(E59<=Params!$B$6,"Mid","High")) -> Mid
A60: R059 | B60: 46247 | C60: Lahore | D60: Airport | E60: 605 | F60: Cash | G60: Completed | H60: 4 | I60: =TEXT(B60,"dddd") -> Thursday | J60: =WEEKNUM(B60,2) -> 33 | K60: =C60&" -> "&D60 -> Lahore -> Airport | L60: =IF(E60<Params!$B$5,"Low",IF(E60<=Params!$B$6,"Mid","High")) -> Mid
A61: R060 | B61: 46246 | C61: Johar Town | D61: Cantt | E61: 606 | F61: Cash | G61: Completed | H61: 4 | I61: =TEXT(B61,"dddd") -> Wednesday | J61: =WEEKNUM(B61,2) -> 33 | K61: =C61&" -> "&D61 -> Johar Town -> Cantt | L61: =IF(E61<Params!$B$5,"Low",IF(E61<=Params!$B$6,"Mid","High")) -> Mid
A62: R061 | B62: 46245 | C62: Johar Town | D62: Gulberg | E62: 721 | F62: Card | G62: Completed | H62: 4 | I62: =TEXT(B62,"dddd") -> Tuesday | J62: =WEEKNUM(B62,2) -> 33 | K62: =C62&" -> "&D62 -> Johar Town -> Gulberg | L62: =IF(E62<Params!$B$5,"Low",IF(E62<=Params!$B$6,"Mid","High")) -> Mid
A63: R062 | B63: 46256 | C63: Bahria Town | D63: DHA | E63: 386 | F63: Card | G63: Completed | H63: 4 | I63: =TEXT(B63,"dddd") -> Saturday | J63: =WEEKNUM(B63,2) -> 34 | K63: =C63&" -> "&D63 -> Bahria Town -> DHA | L63: =IF(E63<Params!$B$5,"Low",IF(E63<=Params!$B$6,"Mid","High")) -> Low
A64: R063 | B64: 46236 | C64: Gulberg | D64: Askari | E64: 857 | F64: Wallet | G64: Completed | H64: 4 | I64: =TEXT(B64,"dddd") -> Sunday | J64: =WEEKNUM(B64,2) -> 31 | K64: =C64&" -> "&D64 -> Gulberg -> Askari | L64: =IF(E64<Params!$B$5,"Low",IF(E64<=Params!$B$6,"Mid","High")) -> High
A65: R064 | B65: 46254 | C65: Gulberg | D65: Askari | E65: 539 | F65: Card | G65: Completed | H65: 4 | I65: =TEXT(B65,"dddd") -> Thursday | J65: =WEEKNUM(B65,2) -> 34 | K65: =C65&" -> "&D65 -> Gulberg -> Askari | L65: =IF(E65<Params!$B$5,"Low",IF(E65<=Params!$B$6,"Mid","High")) -> Low
A66: R065 | B66: 46235 | C66: Model Town | D66: Faisal Town | E66: 1033 | F66: Cash | G66: Cancelled | I66: =TEXT(B66,"dddd") -> Saturday | J66: =WEEKNUM(B66,2) -> 31 | K66: =C66&" -> "&D66 -> Model Town -> Faisal Town | L66: =IF(E66<Params!$B$5,"Low",IF(E66<=Params!$B$6,"Mid","High")) -> High
A67: R066 | B67: 46264 | C67: Bahria Town | D67: Faisal Town | E67: 405 | F67: Wallet | G67: Cancelled | I67: =TEXT(B67,"dddd") -> Sunday | J67: =WEEKNUM(B67,2) -> 35 | K67: =C67&" -> "&D67 -> Bahria Town -> Faisal Town | L67: =IF(E67<Params!$B$5,"Low",IF(E67<=Params!$B$6,"Mid","High")) -> Low
A68: R067 | B68: 46251 | C68: Johar Town | D68: Askari | E68: 818 | F68: Card | G68: Completed | H68: 5 | I68: =TEXT(B68,"dddd") -> Monday | J68: =WEEKNUM(B68,2) -> 34 | K68: =C68&" -> "&D68 -> Johar Town -> Askari | L68: =IF(E68<Params!$B$5,"Low",IF(E68<=Params!$B$6,"Mid","High")) -> Mid
A69: R068 | B69: 46239 | C69: Model Town | D69: Askari | E69: 926 | F69: Wallet | G69: Completed | H69: 3 | I69: =TEXT(B69,"dddd") -> Wednesday | J69: =WEEKNUM(B69,2) -> 32 | K69: =C69&" -> "&D69 -> Model Town -> Askari | L69: =IF(E69<Params!$B$5,"Low",IF(E69<=Params!$B$6,"Mid","High")) -> High
A70: R069 | B70: 46254 | C70: Johar Town | D70: Askari | E70: 150 | F70: Card | G70: Completed | H70: 4 | I70: =TEXT(B70,"dddd") -> Thursday | J70: =WEEKNUM(B70,2) -> 34 | K70: =C70&" -> "&D70 -> Johar Town -> Askari | L70: =IF(E70<Params!$B$5,"Low",IF(E70<=Params!$B$6,"Mid","High")) -> Low
A71: R070 | B71: 46260 | C71: Bahria Town | D71: Airport | E71: 1054 | F71: Card | G71: Completed | H71: 5 | I71: =TEXT(B71,"dddd") -> Wednesday | J71: =WEEKNUM(B71,2) -> 35 | K71: =C71&" -> "&D71 -> Bahria Town -> Airport | L71: =IF(E71<Params!$B$5,"Low",IF(E71<=Params!$B$6,"Mid","High")) -> High
A72: R071 | B72: 46250 | C72: DHA | D72: Gulberg | E72: 731 | F72: Wallet | G72: Completed | H72: 5 | I72: =TEXT(B72,"dddd") -> Sunday | J72: =WEEKNUM(B72,2) -> 33 | K72: =C72&" -> "&D72 -> DHA -> Gulberg | L72: =IF(E72<Params!$B$5,"Low",IF(E72<=Params!$B$6,"Mid","High")) -> Mid
A73: R072 | B73: 46245 | C73: Gulberg | D73: Cantt | E73: 785 | F73: Cash | G73: Completed | H73: 3 | I73: =TEXT(B73,"dddd") -> Tuesday | J73: =WEEKNUM(B73,2) -> 33 | K73: =C73&" -> "&D73 -> Gulberg -> Cantt | L73: =IF(E73<Params!$B$5,"Low",IF(E73<=Params!$B$6,"Mid","High")) -> Mid
A74: R073 | B74: 46235 | C74: Lahore | D74: Cantt | E74: 1123 | F74: Wallet | G74: Cancelled | I74: =TEXT(B74,"dddd") -> Saturday | J74: =WEEKNUM(B74,2) -> 31 | K74: =C74&" -> "&D74 -> Lahore -> Cantt | L74: =IF(E74<Params!$B$5,"Low",IF(E74<=Params!$B$6,"Mid","High")) -> High
A75: R074 | B75: 46237 | C75: Iqbal Town | D75: Askari | E75: 548 | F75: Wallet | G75: Completed | H75: 4 | I75: =TEXT(B75,"dddd") -> Monday | J75: =WEEKNUM(B75,2) -> 32 | K75: =C75&" -> "&D75 -> Iqbal Town -> Askari | L75: =IF(E75<Params!$B$5,"Low",IF(E75<=Params!$B$6,"Mid","High")) -> Mid
A76: R075 | B76: 46247 | C76: Model Town | D76: Model Town | E76: 161 | F76: Cash | G76: Completed | H76: 3 | I76: =TEXT(B76,"dddd") -> Thursday | J76: =WEEKNUM(B76,2) -> 33 | K76: =C76&" -> "&D76 -> Model Town -> Model Town | L76: =IF(E76<Params!$B$5,"Low",IF(E76<=Params!$B$6,"Mid","High")) -> Low
A77: R076 | B77: 46240 | C77: Iqbal Town | D77: DHA | E77: 660 | F77: Cash | G77: Completed | H77: 4 | I77: =TEXT(B77,"dddd") -> Thursday | J77: =WEEKNUM(B77,2) -> 32 | K77: =C77&" -> "&D77 -> Iqbal Town -> DHA | L77: =IF(E77<Params!$B$5,"Low",IF(E77<=Params!$B$6,"Mid","High")) -> Mid
A78: R077 | B78: 46256 | C78: Bahria Town | D78: Airport | E78: 1183 | F78: Card | G78: Cancelled | I78: =TEXT(B78,"dddd") -> Saturday | J78: =WEEKNUM(B78,2) -> 34 | K78: =C78&" -> "&D78 -> Bahria Town -> Airport | L78: =IF(E78<Params!$B$5,"Low",IF(E78<=Params!$B$6,"Mid","High")) -> High
A79: R078 | B79: 46252 | C79: Iqbal Town | D79: Model Town | E79: 1122 | F79: Card | G79: Completed | H79: 3 | I79: =TEXT(B79,"dddd") -> Tuesday | J79: =WEEKNUM(B79,2) -> 34 | K79: =C79&" -> "&D79 -> Iqbal Town -> Model Town | L79: =IF(E79<Params!$B$5,"Low",IF(E79<=Params!$B$6,"Mid","High")) -> High
A80: R079 | B80: 46261 | C80: Johar Town | D80: Airport | E80: 639 | F80: Card | G80: Completed | H80: 5 | I80: =TEXT(B80,"dddd") -> Thursday | J80: =WEEKNUM(B80,2) -> 35 | K80: =C80&" -> "&D80 -> Johar Town -> Airport | L80: =IF(E80<Params!$B$5,"Low",IF(E80<=Params!$B$6,"Mid","High")) -> Mid
A81: R080 | B81: 46244 | C81: Model Town | D81: Township | E81: 837 | F81: Card | G81: Cancelled | I81: =TEXT(B81,"dddd") -> Monday | J81: =WEEKNUM(B81,2) -> 33 | K81: =C81&" -> "&D81 -> Model Town -> Township | L81: =IF(E81<Params!$B$5,"Low",IF(E81<=Params!$B$6,"Mid","High")) -> High
A82: R081 | B82: 46237 | C82: DHA | D82: Model Town | E82: 623 | F82: Card | G82: Completed | H82: 5 | I82: =TEXT(B82,"dddd") -> Monday | J82: =WEEKNUM(B82,2) -> 32 | K82: =C82&" -> "&D82 -> DHA -> Model Town | L82: =IF(E82<Params!$B$5,"Low",IF(E82<=Params!$B$6,"Mid","High")) -> Mid
A83: R082 | B83: 46241 | C83: Gulberg | D83: Askari | E83: 984 | F83: Card | G83: Completed | H83: 4 | I83: =TEXT(B83,"dddd") -> Friday | J83: =WEEKNUM(B83,2) -> 32 | K83: =C83&" -> "&D83 -> Gulberg -> Askari | L83: =IF(E83<Params!$B$5,"Low",IF(E83<=Params!$B$6,"Mid","High")) -> High
A84: R083 | B84: 46236 | C84: Model Town | D84: Askari | E84: 947 | F84: Wallet | G84: Cancelled | I84: =TEXT(B84,"dddd") -> Sunday | J84: =WEEKNUM(B84,2) -> 31 | K84: =C84&" -> "&D84 -> Model Town -> Askari | L84: =IF(E84<Params!$B$5,"Low",IF(E84<=Params!$B$6,"Mid","High")) -> High
A85: R084 | B85: 46235 | C85: Wapda Town | D85: Airport | E85: 162 | F85: Card | G85: Completed | H85: 4 | I85: =TEXT(B85,"dddd") -> Saturday | J85: =WEEKNUM(B85,2) -> 31 | K85: =C85&" -> "&D85 -> Wapda Town -> Airport | L85: =IF(E85<Params!$B$5,"Low",IF(E85<=Params!$B$6,"Mid","High")) -> Low
A86: R085 | B86: 46262 | C86: Wapda Town | D86: Cantt | E86: 1149 | F86: Cash | G86: Completed | H86: 4 | I86: =TEXT(B86,"dddd") -> Friday | J86: =WEEKNUM(B86,2) -> 35 | K86: =C86&" -> "&D86 -> Wapda Town -> Cantt | L86: =IF(E86<Params!$B$5,"Low",IF(E86<=Params!$B$6,"Mid","High")) -> High
A87: R086 | B87: 46235 | C87: Wapda Town | D87: Faisal Town | E87: 978 | F87: Wallet | G87: Completed | H87: 4 | I87: =TEXT(B87,"dddd") -> Saturday | J87: =WEEKNUM(B87,2) -> 31 | K87: =C87&" -> "&D87 -> Wapda Town -> Faisal Town | L87: =IF(E87<Params!$B$5,"Low",IF(E87<=Params!$B$6,"Mid","High")) -> High
A88: R087 | B88: 46264 | C88: DHA | D88: DHA | E88: 956 | F88: Wallet | G88: Completed | H88: 3 | I88: =TEXT(B88,"dddd") -> Sunday | J88: =WEEKNUM(B88,2) -> 35 | K88: =C88&" -> "&D88 -> DHA -> DHA | L88: =IF(E88<Params!$B$5,"Low",IF(E88<=Params!$B$6,"Mid","High")) -> High
A89: R088 | B89: 46237 | C89: Wapda Town | D89: Model Town | E89: 1095 | F89: Cash | G89: Completed | H89: 4 | I89: =TEXT(B89,"dddd") -> Monday | J89: =WEEKNUM(B89,2) -> 32 | K89: =C89&" -> "&D89 -> Wapda Town -> Model Town | L89: =IF(E89<Params!$B$5,"Low",IF(E89<=Params!$B$6,"Mid","High")) -> High
A90: R089 | B90: 46245 | C90: Model Town | D90: Airport | E90: 819 | F90: Card | G90: Completed | H90: 4 | I90: =TEXT(B90,"dddd") -> Tuesday | J90: =WEEKNUM(B90,2) -> 33 | K90: =C90&" -> "&D90 -> Model Town -> Airport | L90: =IF(E90<Params!$B$5,"Low",IF(E90<=Params!$B$6,"Mid","High")) -> Mid
A91: R090 | B91: 46243 | C91: Wapda Town | D91: Township | E91: 317 | F91: Card | G91: Completed | H91: 5 | I91: =TEXT(B91,"dddd") -> Sunday | J91: =WEEKNUM(B91,2) -> 32 | K91: =C91&" -> "&D91 -> Wapda Town -> Township | L91: =IF(E91<Params!$B$5,"Low",IF(E91<=Params!$B$6,"Mid","High")) -> Low
A92: R091 | B92: 46236 | C92: Bahria Town | D92: Cantt | E92: 290 | F92: Wallet | G92: Completed | H92: 3 | I92: =TEXT(B92,"dddd") -> Sunday | J92: =WEEKNUM(B92,2) -> 31 | K92: =C92&" -> "&D92 -> Bahria Town -> Cantt | L92: =IF(E92<Params!$B$5,"Low",IF(E92<=Params!$B$6,"Mid","High")) -> Low
A93: R092 | B93: 46242 | C93: Model Town | D93: DHA | E93: 462 | F93: Cash | G93: Completed | H93: 5 | I93: =TEXT(B93,"dddd") -> Saturday | J93: =WEEKNUM(B93,2) -> 32 | K93: =C93&" -> "&D93 -> Model Town -> DHA | L93: =IF(E93<Params!$B$5,"Low",IF(E93<=Params!$B$6,"Mid","High")) -> Low
A94: R093 | B94: 46238 | C94: Model Town | D94: Airport | E94: 674 | F94: Card | G94: Completed | H94: 5 | I94: =TEXT(B94,"dddd") -> Tuesday | J94: =WEEKNUM(B94,2) -> 32 | K94: =C94&" -> "&D94 -> Model Town -> Airport | L94: =IF(E94<Params!$B$5,"Low",IF(E94<=Params!$B$6,"Mid","High")) -> Mid
A95: R094 | B95: 46258 | C95: Gulberg | D95: Model Town | E95: 787 | F95: Cash | G95: Completed | H95: 4 | I95: =TEXT(B95,"dddd") -> Monday | J95: =WEEKNUM(B95,2) -> 35 | K95: =C95&" -> "&D95 -> Gulberg -> Model Town | L95: =IF(E95<Params!$B$5,"Low",IF(E95<=Params!$B$6,"Mid","High")) -> Mid
A96: R095 | B96: 46253 | C96: Wapda Town | D96: Askari | E96: 556 | F96: Cash | G96: Completed | H96: 5 | I96: =TEXT(B96,"dddd") -> Wednesday | J96: =WEEKNUM(B96,2) -> 34 | K96: =C96&" -> "&D96 -> Wapda Town -> Askari | L96: =IF(E96<Params!$B$5,"Low",IF(E96<=Params!$B$6,"Mid","High")) -> Mid
... A98: R097 | B98: 46252 | C98: Wapda Town | D98: Faisal Town | E98: 291 | F98: Wallet | G98: Completed | H98: 3 | I98: =TEXT(B98,"dddd") -> Tuesday | J98: =WEEKNUM(B98,2) -> 34 | K98: =C98&" -> "&D98 -> Wapda Town -> Faisal Town | L98: =IF(E98<Params!$B$5,"Low",IF(E98<=Params!$B$6,"Mid","High")) -> Low
A99: R098 | B99: 46262 | C99: Wapda Town | D99: Airport | E99: 366 | F99: Card | G99: Cancelled | I99: =TEXT(B99,"dddd") -> Friday | J99: =WEEKNUM(B99,2) -> 35 | K99: =C99&" -> "&D99 -> Wapda Town -> Airport | L99: =IF(E99<Params!$B$5,"Low",IF(E99<=Params!$B$6,"Mid","High")) -> Low
A100: R099 | B100: 46255 | C100: Iqbal Town | D100: Model Town | E100: 1041 | F100: Cash | G100: Completed | H100: 5 | I100: =TEXT(B100,"dddd") -> Friday | J100: =WEEKNUM(B100,2) -> 34 | K100: =C100&" -> "&D100 -> Iqbal Town -> Model Town | L100: =IF(E100<Params!$B$5,"Low",IF(E100<=Params!$B$6,"Mid","High")) -> High
A101: R100 | B101: 46243 | C101: Iqbal Town | D101: Airport | E101: 1042 | F101: Wallet | G101: Completed | H101: 4 | I101: =TEXT(B101,"dddd") -> Sunday | J101: =WEEKNUM(B101,2) -> 32 | K101: =C101&" -> "&D101 -> Iqbal Town -> Airport | L101: =IF(E101<Params!$B$5,"Low",IF(E101<=Params!$B$6,"Mid","High")) -> High
...

Sheet Params
A1: Model Parameters
A2: Fare-tier thresholds = 33rd / 67th percentile of completed-ride fares, computed once from the dataset (edit the yellow cells to re-tier).
A4: Parameter | B4: Value
A5: Low/Mid fare threshold (33rd pct. of completed fares) | B5: 548
A6: Mid/High fare threshold (67th pct. of completed fares) | B6: 822

Sheet Date Table
A1: Date Table
A2: Dedicated date dimension for August 2026 (the full span of the ride log).
A4: Date | B4: Day | C4: Weekday | D4: Week No. | E4: Month | F4: Is Weekend
A5: 46235 | B5: =DAY(A5) -> 1 | C5: =TEXT(A5,"dddd") -> Saturday | D5: =WEEKNUM(A5,2) -> 31 | E5: =TEXT(A5,"mmmm yyyy") -> August 2026 | F5: =IF(WEEKDAY(A5,2)>5,"Yes","No") -> Yes
A6: 46236 | B6: =DAY(A6) -> 2 | C6: =TEXT(A6,"dddd") -> Sunday | D6: =WEEKNUM(A6,2) -> 31 | E6: =TEXT(A6,"mmmm yyyy") -> August 2026 | F6: =IF(WEEKDAY(A6,2)>5,"Yes","No") -> Yes
A7: 46237 | B7: =DAY(A7) -> 3 | C7: =TEXT(A7,"dddd") -> Monday | D7: =WEEKNUM(A7,2) -> 32 | E7: =TEXT(A7,"mmmm yyyy") -> August 2026 | F7: =IF(WEEKDAY(A7,2)>5,"Yes","No") -> No
A8: 46238 | B8: =DAY(A8) -> 4 | C8: =TEXT(A8,"dddd") -> Tuesday | D8: =WEEKNUM(A8,2) -> 32 | E8: =TEXT(A8,"mmmm yyyy") -> August 2026 | F8: =IF(WEEKDAY(A8,2)>5,"Yes","No") -> No
A9: 46239 | B9: =DAY(A9) -> 5 | C9: =TEXT(A9,"dddd") -> Wednesday | D9: =WEEKNUM(A9,2) -> 32 | E9: =TEXT(A9,"mmmm yyyy") -> August 2026 | F9: =IF(WEEKDAY(A9,2)>5,"Yes","No") -> No
A10: 46240 | B10: =DAY(A10) -> 6 | C10: =TEXT(A10,"dddd") -> Thursday | D10: =WEEKNUM(A10,2) -> 32 | E10: =TEXT(A10,"mmmm yyyy") -> August 2026 | F10: =IF(WEEKDAY(A10,2)>5,"Yes","No") -> No
A11: 46241 | B11: =DAY(A11) -> 7 | C11: =TEXT(A11,"dddd") -> Friday | D11: =WEEKNUM(A11,2) -> 32 | E11: =TEXT(A11,"mmmm yyyy") -> August 2026 | F11: =IF(WEEKDAY(A11,2)>5,"Yes","No") -> No
A12: 46242 | B12: =DAY(A12) -> 8 | C12: =TEXT(A12,"dddd") -> Saturday | D12: =WEEKNUM(A12,2) -> 32 | E12: =TEXT(A12,"mmmm yyyy") -> August 2026 | F12: =IF(WEEKDAY(A12,2)>5,"Yes","No") -> Yes
A13: 46243 | B13: =DAY(A13) -> 9 | C13: =TEXT(A13,"dddd") -> Sunday | D13: =WEEKNUM(A13,2) -> 32 | E13: =TEXT(A13,"mmmm yyyy") -> August 2026 | F13: =IF(WEEKDAY(A13,2)>5,"Yes","No") -> Yes
A14: 46244 | B14: =DAY(A14) -> 10 | C14: =TEXT(A14,"dddd") -> Monday | D14: =WEEKNUM(A14,2) -> 33 | E14: =TEXT(A14,"mmmm yyyy") -> August 2026 | F14: =IF(WEEKDAY(A14,2)>5,"Yes","No") -> No
A15: 46245 | B15: =DAY(A15) -> 11 | C15: =TEXT(A15,"dddd") -> Tuesday | D15: =WEEKNUM(A15,2) -> 33 | E15: =TEXT(A15,"mmmm yyyy") -> August 2026 | F15: =IF(WEEKDAY(A15,2)>5,"Yes","No") -> No
A16: 46246 | B16: =DAY(A16) -> 12 | C16: =TEXT(A16,"dddd") -> Wednesday | D16: =WEEKNUM(A16,2) -> 33 | E16: =TEXT(A16,"mmmm yyyy") -> August 2026 | F16: =IF(WEEKDAY(A16,2)>5,"Yes","No") -> No
... A35: 46265 | B35: =DAY(A35) -> 31 | C35: =TEXT(A35,"dddd") -> Monday | D35: =WEEKNUM(A35,2) -> 36 | E35: =TEXT(A35,"mmmm yyyy") -> August 2026 | F35: =IF(WEEKDAY(A35,2)>5,"Yes","No") -> No

Sheet KPI Summary
A1: Core KPI Summary
A2: Equivalent of the Power BI measures table — validate these against your DAX.
A4: Measure | B4: Value | C4: Notes
A5: Total Rides | B5: =COUNTA('Raw Data'!$A$2:$A$121) -> 120 | C5: All logged rides
A6: Completed Rides | B6: =COUNTIF('Raw Data'!$G$2:$G$121,"Completed") -> 96 | C6: Status = Completed
A7: Cancelled Rides | B7: =COUNTIF('Raw Data'!$G$2:$G$121,"Cancelled") -> 24 | C7: Status = Cancelled
A8: Completion Rate | B8: =B6/B5 -> 0.8
A9: Cancellation Rate | B9: =B7/B5 -> 0.2
A10: Total Revenue | B10: =SUMIF('Raw Data'!$G$2:$G$121,"Completed",'Raw Data'!$E$2:$E$121) -> 65427 | C10: Completed rides only
A11: Average Fare (Completed) | B11: =AVERAGEIF('Raw Data'!$G$2:$G$121,"Completed",'Raw Data'!$E$2:$E$121) -> 681.53125
A12: Revenue per Completed Ride | B12: =B10/B6 -> 681.53125 | C12: Total Revenue divided by Completed Rides (same as Avg Fare here since no surge/tips)
A13: Average Rating | B13: =AVERAGE('Raw Data'!$H$2:$H$121) -> 3.9583333 | C13: Ratings only exist for completed rides

Sheet Weekday Analysis
A1: Cancellation & Demand by Weekday
A2: Hour-of-day data is not available in this dataset; weekday is the finest time grain we can analyze.
A4: Weekday | B4: Total Rides | C4: Completed | D4: Cancelled | E4: Cancellation Rate | F4: Revenue
A5: Monday | B5: =COUNTIF('Raw Data'!$I$2:$I$121,A5) -> 20 | C5: =COUNTIFS('Raw Data'!$I$2:$I$121,A5,'Raw Data'!$G$2:$G$121,"Completed") -> 16 | D5: =COUNTIFS('Raw Data'!$I$2:$I$121,A5,'Raw Data'!$G$2:$G$121,"Cancelled") -> 4 | E5: =D5/B5 -> 0.2 | F5: =SUMIFS('Raw Data'!$E$2:$E$121,'Raw Data'!$I$2:$I$121,A5,'Raw Data'!$G$2:$G$121,"Completed") -> 10323
A6: Tuesday | B6: =COUNTIF('Raw Data'!$I$2:$I$121,A6) -> 13 | C6: =COUNTIFS('Raw Data'!$I$2:$I$121,A6,'Raw Data'!$G$2:$G$121,"Completed") -> 12 | D6: =COUNTIFS('Raw Data'!$I$2:$I$121,A6,'Raw Data'!$G$2:$G$121,"Cancelled") -> 1 | E6: =D6/B6 -> 0.076923077 | F6: =SUMIFS('Raw Data'!$E$2:$E$121,'Raw Data'!$I$2:$I$121,A6,'Raw Data'!$G$2:$G$121,"Completed") -> 7546
A7: Wednesday | B7: =COUNTIF('Raw Data'!$I$2:$I$121,A7) -> 18 | C7: =COUNTIFS('Raw Data'!$I$2:$I$121,A7,'Raw Data'!$G$2:$G$121,"Completed") -> 17 | D7: =COUNTIFS('Raw Data'!$I$2:$I$121,A7,'Raw Data'!$G$2:$G$121,"Cancelled") -> 1 | E7: =D7/B7 -> 0.055555556 | F7: =SUMIFS('Raw Data'!$E$2:$E$121,'Raw Data'!$I$2:$I$121,A7,'Raw Data'!$G$2:$G$121,"Completed") -> 11667
A8: Thursday | B8: =COUNTIF('Raw Data'!$I$2:$I$121,A8) -> 9 | C8: =COUNTIFS('Raw Data'!$I$2:$I$121,A8,'Raw Data'!$G$2:$G$121,"Completed") -> 9 | D8: =COUNTIFS('Raw Data'!$I$2:$I$121,A8,'Raw Data'!$G$2:$G$121,"Cancelled") -> 0 | E8: =D8/B8 -> 0 | F8: =SUMIFS('Raw Data'!$E$2:$E$121,'Raw Data'!$I$2:$I$121,A8,'Raw Data'!$G$2:$G$121,"Completed") -> 5483
A9: Friday | B9: =COUNTIF('Raw Data'!$I$2:$I$121,A9) -> 14 | C9: =COUNTIFS('Raw Data'!$I$2:$I$121,A9,'Raw Data'!$G$2:$G$121,"Completed") -> 11 | D9: =COUNTIFS('Raw Data'!$I$2:$I$121,A9,'Raw Data'!$G$2:$G$121,"Cancelled") -> 3 | E9: =D9/B9 -> 0.21428571 | F9: =SUMIFS('Raw Data'!$E$2:$E$121,'Raw Data'!$I$2:$I$121,A9,'Raw Data'!$G$2:$G$121,"Completed") -> 9176
A10: Saturday | B10: =COUNTIF('Raw Data'!$I$2:$I$121,A10) -> 23 | C10: =COUNTIFS('Raw Data'!$I$2:$I$121,A10,'Raw Data'!$G$2:$G$121,"Completed") -> 14 | D10: =COUNTIFS('Raw Data'!$I$2:$I$121,A10,'Raw Data'!$G$2:$G$121,"Cancelled") -> 9 | E10: =D10/B10 -> 0.39130435 | F10: =SUMIFS('Raw Data'!$E$2:$E$121,'Raw Data'!$I$2:$I$121,A10,'Raw Data'!$G$2:$G$121,"Completed") -> 9322
A11: Sunday | B11: =COUNTIF('Raw Data'!$I$2:$I$121,A11) -> 23 | C11: =COUNTIFS('Raw Data'!$I$2:$I$121,A11,'Raw Data'!$G$2:$G$121,"Completed") -> 17 | D11: =COUNTIFS('Raw Data'!$I$2:$I$121,A11,'Raw Data'!$G$2:$G$121,"Cancelled") -> 6 | E11: =D11/B11 -> 0.26086957 | F11: =SUMIFS('Raw Data'!$E$2:$E$121,'Raw Data'!$I$2:$I$121,A11,'Raw Data'!$G$2:$G$121,"Completed") -> 11910

Sheet Weekly Trend
A1: Week-over-Week Trend
A2: Only one calendar month of data exists, so trend is shown week-over-week rather than month-over-month. Week 31 is partial (2 days).
A4: Week No. | B4: Total Rides | C4: Completed | D4: Cancelled | E4: Cancellation Rate | F4: Revenue | G4: Revenue vs Prior Week | H4: % Change vs Prior Week
A5: 31 | B5: =COUNTIF('Raw Data'!$J$2:$J$121,A5) -> 13 | C5: =COUNTIFS('Raw Data'!$J$2:$J$121,A5,'Raw Data'!$G$2:$G$121,"Completed") -> 9 | D5: =COUNTIFS('Raw Data'!$J$2:$J$121,A5,'Raw Data'!$G$2:$G$121,"Cancelled") -> 4 | E5: =D5/B5 -> 0.30769231 | F5: =SUMIFS('Raw Data'!$E$2:$E$121,'Raw Data'!$J$2:$J$121,A5,'Raw Data'!$G$2:$G$121,"Completed") -> 5342 | G5: ="" | H5: =""
A6: 32 | B6: =COUNTIF('Raw Data'!$J$2:$J$121,A6) -> 28 | C6: =COUNTIFS('Raw Data'!$J$2:$J$121,A6,'Raw Data'!$G$2:$G$121,"Completed") -> 24 | D6: =COUNTIFS('Raw Data'!$J$2:$J$121,A6,'Raw Data'!$G$2:$G$121,"Cancelled") -> 4 | E6: =D6/B6 -> 0.14285714 | F6: =SUMIFS('Raw Data'!$E$2:$E$121,'Raw Data'!$J$2:$J$121,A6,'Raw Data'!$G$2:$G$121,"Completed") -> 15241 | G6: =F6-F5 -> 9899 | H6: =IF(F5=0,"",(F6-F5)/F5) -> 1.8530513
A7: 33 | B7: =COUNTIF('Raw Data'!$J$2:$J$121,A7) -> 18 | C7: =COUNTIFS('Raw Data'!$J$2:$J$121,A7,'Raw Data'!$G$2:$G$121,"Completed") -> 15 | D7: =COUNTIFS('Raw Data'!$J$2:$J$121,A7,'Raw Data'!$G$2:$G$121,"Cancelled") -> 3 | E7: =D7/B7 -> 0.16666667 | F7: =SUMIFS('Raw Data'!$E$2:$E$121,'Raw Data'!$J$2:$J$121,A7,'Raw Data'!$G$2:$G$121,"Completed") -> 10381 | G7: =F7-F6 -> -4860 | H7: =IF(F6=0,"",(F7-F6)/F6) -> -0.31887671
A8: 34 | B8: =COUNTIF('Raw Data'!$J$2:$J$121,A8) -> 36 | C8: =COUNTIFS('Raw Data'!$J$2:$J$121,A8,'Raw Data'!$G$2:$G$121,"Completed") -> 30 | D8: =COUNTIFS('Raw Data'!$J$2:$J$121,A8,'Raw Data'!$G$2:$G$121,"Cancelled") -> 6 | E8: =D8/B8 -> 0.16666667 | F8: =SUMIFS('Raw Data'!$E$2:$E$121,'Raw Data'!$J$2:$J$121,A8,'Raw Data'!$G$2:$G$121,"Completed") -> 21188 | G8: =F8-F7 -> 10807 | H8: =IF(F7=0,"",(F8-F7)/F7) -> 1.0410365
A9: 35 | B9: =COUNTIF('Raw Data'!$J$2:$J$121,A9) -> 25 | C9: =COUNTIFS('Raw Data'!$J$2:$J$121,A9,'Raw Data'!$G$2:$G$121,"Completed") -> 18 | D9: =COUNTIFS('Raw Data'!$J$2:$J$121,A9,'Raw Data'!$G$2:$G$121,"Cancelled") -> 7 | E9: =D9/B9 -> 0.28 | F9: =SUMIFS('Raw Data'!$E$2:$E$121,'Raw Data'!$J$2:$J$121,A9,'Raw Data'!$G$2:$G$121,"Completed") -> 13275 | G9: =F9-F8 -> -7913 | H9: =IF(F8=0,"",(F9-F8)/F8) -> -0.37346611

Sheet Location Analysis
A1: Revenue & Cancellation by Pickup Location
A2: Ranked by revenue contribution; use to spot high-volume/low-revenue and low-volume/high-fare segments.
A4: Pickup Location | B4: Total Rides | C4: Completed | D4: Cancelled | E4: Cancellation Rate | F4: Revenue | G4: Revenue % of Total | H4: Revenue Rank | I4: Avg Fare (Completed)
A5: Bahria Town | B5: =COUNTIF('Raw Data'!$C$2:$C$121,A5) -> 15 | C5: =COUNTIFS('Raw Data'!$C$2:$C$121,A5,'Raw Data'!$G$2:$G$121,"Completed") -> 12 | D5: =COUNTIFS('Raw Data'!$C$2:$C$121,A5,'Raw Data'!$G$2:$G$121,"Cancelled") -> 3 | E5: =D5/B5 -> 0.2 | F5: =SUMIFS('Raw Data'!$E$2:$E$121,'Raw Data'!$C$2:$C$121,A5,'Raw Data'!$G$2:$G$121,"Completed") -> 8145 | G5: =F5/'KPI Summary'!$B$10 -> 0.12448989 | H5: =RANK(F5,$F$5:$F$12) -> 6 | I5: =IFERROR(F5/C5,0) -> 678.75
A6: DHA | B6: =COUNTIF('Raw Data'!$C$2:$C$121,A6) -> 7 | C6: =COUNTIFS('Raw Data'!$C$2:$C$121,A6,'Raw Data'!$G$2:$G$121,"Completed") -> 6 | D6: =COUNTIFS('Raw Data'!$C$2:$C$121,A6,'Raw Data'!$G$2:$G$121,"Cancelled") -> 1 | E6: =D6/B6 -> 0.14285714 | F6: =SUMIFS('Raw Data'!$E$2:$E$121,'Raw Data'!$C$2:$C$121,A6,'Raw Data'!$G$2:$G$121,"Completed") -> 3514 | G6: =F6/'KPI Summary'!$B$10 -> 0.053708714 | H6: =RANK(F6,$F$5:$F$12) -> 8 | I6: =IFERROR(F6/C6,0) -> 585.66667
A7: Gulberg | B7: =COUNTIF('Raw Data'!$C$2:$C$121,A7) -> 15 | C7: =COUNTIFS('Raw Data'!$C$2:$C$121,A7,'Raw Data'!$G$2:$G$121,"Completed") -> 14 | D7: =COUNTIFS('Raw Data'!$C$2:$C$121,A7,'Raw Data'!$G$2:$G$121,"Cancelled") -> 1 | E7: =D7/B7 -> 0.066666667 | F7: =SUMIFS('Raw Data'!$E$2:$E$121,'Raw Data'!$C$2:$C$121,A7,'Raw Data'!$G$2:$G$121,"Completed") -> 8757 | G7: =F7/'KPI Summary'!$B$10 -> 0.13384383 | H7: =RANK(F7,$F$5:$F$12) -> 4 | I7: =IFERROR(F7/C7,0) -> 625.5
A8: Iqbal Town | B8: =COUNTIF('Raw Data'!$C$2:$C$121,A8) -> 15 | C8: =COUNTIFS('Raw Data'!$C$2:$C$121,A8,'Raw Data'!$G$2:$G$121,"Completed") -> 12 | D8: =COUNTIFS('Raw Data'!$C$2:$C$121,A8,'Raw Data'!$G$2:$G$121,"Cancelled") -> 3 | E8: =D8/B8 -> 0.2 | F8: =SUMIFS('Raw Data'!$E$2:$E$121,'Raw Data'!$C$2:$C$121,A8,'Raw Data'!$G$2:$G$121,"Completed") -> 8466 | G8: =F8/'KPI Summary'!$B$10 -> 0.12939612 | H8: =RANK(F8,$F$5:$F$12) -> 5 | I8: =IFERROR(F8/C8,0) -> 705.5
A9: Johar Town | B9: =COUNTIF('Raw Data'!$C$2:$C$121,A9) -> 21 | C9: =COUNTIFS('Raw Data'!$C$2:$C$121,A9,'Raw Data'!$G$2:$G$121,"Completed") -> 17 | D9: =COUNTIFS('Raw Data'!$C$2:$C$121,A9,'Raw Data'!$G$2:$G$121,"Cancelled") -> 4 | E9: =D9/B9 -> 0.19047619 | F9: =SUMIFS('Raw Data'!$E$2:$E$121,'Raw Data'!$C$2:$C$121,A9,'Raw Data'!$G$2:$G$121,"Completed") -> 11323 | G9: =F9/'KPI Summary'!$B$10 -> 0.17306311 | H9: =RANK(F9,$F$5:$F$12) -> 1 | I9: =IFERROR(F9/C9,0) -> 666.05882
A10: Lahore | B10: =COUNTIF('Raw Data'!$C$2:$C$121,A10) -> 10 | C10: =COUNTIFS('Raw Data'!$C$2:$C$121,A10,'Raw Data'!$G$2:$G$121,"Completed") -> 7 | D10: =COUNTIFS('Raw Data'!$C$2:$C$121,A10,'Raw Data'!$G$2:$G$121,"Cancelled") -> 3 | E10: =D10/B10 -> 0.3 | F10: =SUMIFS('Raw Data'!$E$2:$E$121,'Raw Data'!$C$2:$C$121,A10,'Raw Data'!$G$2:$G$121,"Completed") -> 5281 | G10: =F10/'KPI Summary'!$B$10 -> 0.080715912 | H10: =RANK(F10,$F$5:$F$12) -> 7 | I10: =IFERROR(F10/C10,0) -> 754.42857
A11: Model Town | B11: =COUNTIF('Raw Data'!$C$2:$C$121,A11) -> 19 | C11: =COUNTIFS('Raw Data'!$C$2:$C$121,A11,'Raw Data'!$G$2:$G$121,"Completed") -> 14 | D11: =COUNTIFS('Raw Data'!$C$2:$C$121,A11,'Raw Data'!$G$2:$G$121,"Cancelled") -> 5 | E11: =D11/B11 -> 0.26315789 | F11: =SUMIFS('Raw Data'!$E$2:$E$121,'Raw Data'!$C$2:$C$121,A11,'Raw Data'!$G$2:$G$121,"Completed") -> 10139 | G11: =F11/'KPI Summary'!$B$10 -> 0.1549666 | H11: =RANK(F11,$F$5:$F$12) -> 2 | I11: =IFERROR(F11/C11,0) -> 724.21429
A12: Wapda Town | B12: =COUNTIF('Raw Data'!$C$2:$C$121,A12) -> 18 | C12: =COUNTIFS('Raw Data'!$C$2:$C$121,A12,'Raw Data'!$G$2:$G$121,"Completed") -> 14 | D12: =COUNTIFS('Raw Data'!$C$2:$C$121,A12,'Raw Data'!$G$2:$G$121,"Cancelled") -> 4 | E12: =D12/B12 -> 0.22222222 | F12: =SUMIFS('Raw Data'!$E$2:$E$121,'Raw Data'!$C$2:$C$121,A12,'Raw Data'!$G$2:$G$121,"Completed") -> 9802 | G12: =F12/'KPI Summary'!$B$10 -> 0.14981583 | H12: =RANK(F12,$F$5:$F$12) -> 3 | I12: =IFERROR(F12/C12,0) -> 700.14286

Sheet Route Analysis
A1: Route-Level Analysis (Top Corridors)
A2: No ride-type or distance field exists, so pickup->drop-off route is the closest available segment. Only routes with 3+ rides are shown for statistical stability.
A4: Route | B4: Total Rides | C4: Completed | D4: Cancelled | E4: Cancellation Rate | F4: Revenue | G4: Avg Fare (Completed)
A5: Bahria Town -> Airport | B5: =COUNTIF('Raw Data'!$K$2:$K$121,A5) -> 3 | C5: =COUNTIFS('Raw Data'!$K$2:$K$121,A5,'Raw Data'!$G$2:$G$121,"Completed") -> 2 | D5: =COUNTIFS('Raw Data'!$K$2:$K$121,A5,'Raw Data'!$G$2:$G$121,"Cancelled") -> 1 | E5: =D5/B5 -> 0.33333333 | F5: =SUMIFS('Raw Data'!$E$2:$E$121,'Raw Data'!$K$2:$K$121,A5,'Raw Data'!$G$2:$G$121,"Completed") -> 2128 | G5: =IFERROR(F5/C5,0) -> 1064
A6: Bahria Town -> Cantt | B6: =COUNTIF('Raw Data'!$K$2:$K$121,A6) -> 4 | C6: =COUNTIFS('Raw Data'!$K$2:$K$121,A6,'Raw Data'!$G$2:$G$121,"Completed") -> 3 | D6: =COUNTIFS('Raw Data'!$K$2:$K$121,A6,'Raw Data'!$G$2:$G$121,"Cancelled") -> 1 | E6: =D6/B6 -> 0.25 | F6: =SUMIFS('Raw Data'!$E$2:$E$121,'Raw Data'!$K$2:$K$121,A6,'Raw Data'!$G$2:$G$121,"Completed") -> 1641 | G6: =IFERROR(F6/C6,0) -> 547
A7: Gulberg -> Askari | B7: =COUNTIF('Raw Data'!$K$2:$K$121,A7) -> 4 | C7: =COUNTIFS('Raw Data'!$K$2:$K$121,A7,'Raw Data'!$G$2:$G$121,"Completed") -> 4 | D7: =COUNTIFS('Raw Data'!$K$2:$K$121,A7,'Raw Data'!$G$2:$G$121,"Cancelled") -> 0 | E7: =D7/B7 -> 0 | F7: =SUMIFS('Raw Data'!$E$2:$E$121,'Raw Data'!$K$2:$K$121,A7,'Raw Data'!$G$2:$G$121,"Completed") -> 2595 | G7: =IFERROR(F7/C7,0) -> 648.75
A8: Gulberg -> Model Town | B8: =COUNTIF('Raw Data'!$K$2:$K$121,A8) -> 3 | C8: =COUNTIFS('Raw Data'!$K$2:$K$121,A8,'Raw Data'!$G$2:$G$121,"Completed") -> 3 | D8: =COUNTIFS('Raw Data'!$K$2:$K$121,A8,'Raw Data'!$G$2:$G$121,"Cancelled") -> 0 | E8: =D8/B8 -> 0 | F8: =SUMIFS('Raw Data'!$E$2:$E$121,'Raw Data'!$K$2:$K$121,A8,'Raw Data'!$G$2:$G$121,"Completed") -> 2079 | G8: =IFERROR(F8/C8,0) -> 693
A9: Iqbal Town -> Cantt | B9: =COUNTIF('Raw Data'!$K$2:$K$121,A9) -> 3 | C9: =COUNTIFS('Raw Data'!$K$2:$K$121,A9,'Raw Data'!$G$2:$G$121,"Completed") -> 2 | D9: =COUNTIFS('Raw Data'!$K$2:$K$121,A9,'Raw Data'!$G$2:$G$121,"Cancelled") -> 1 | E9: =D9/B9 -> 0.33333333 | F9: =SUMIFS('Raw Data'!$E$2:$E$121,'Raw Data'!$K$2:$K$121,A9,'Raw Data'!$G$2:$G$121,"Completed") -> 1994 | G9: =IFERROR(F9/C9,0) -> 997
A10: Iqbal Town -> Gulberg | B10: =COUNTIF('Raw Data'!$K$2:$K$121,A10) -> 3 | C10: =COUNTIFS('Raw Data'!$K$2:$K$121,A10,'Raw Data'!$G$2:$G$121,"Completed") -> 3 | D10: =COUNTIFS('Raw Data'!$K$2:$K$121,A10,'Raw Data'!$G$2:$G$121,"Cancelled") -> 0 | E10: =D10/B10 -> 0 | F10: =SUMIFS('Raw Data'!$E$2:$E$121,'Raw Data'!$K$2:$K$121,A10,'Raw Data'!$G$2:$G$121,"Completed") -> 829 | G10: =IFERROR(F10/C10,0) -> 276.33333
A11: Iqbal Town -> Model Town | B11: =COUNTIF('Raw Data'!$K$2:$K$121,A11) -> 5 | C11: =COUNTIFS('Raw Data'!$K$2:$K$121,A11,'Raw Data'!$G$2:$G$121,"Completed") -> 4 | D11: =COUNTIFS('Raw Data'!$K$2:$K$121,A11,'Raw Data'!$G$2:$G$121,"Cancelled") -> 1 | E11: =D11/B11 -> 0.2 | F11: =SUMIFS('Raw Data'!$E$2:$E$121,'Raw Data'!$K$2:$K$121,A11,'Raw Data'!$G$2:$G$121,"Completed") -> 3393 | G11: =IFERROR(F11/C11,0) -> 848.25
A12: Johar Town -> Askari | B12: =COUNTIF('Raw Data'!$K$2:$K$121,A12) -> 3 | C12: =COUNTIFS('Raw Data'!$K$2:$K$121,A12,'Raw Data'!$G$2:$G$121,"Completed") -> 3 | D12: =COUNTIFS('Raw Data'!$K$2:$K$121,A12,'Raw Data'!$G$2:$G$121,"Cancelled") -> 0 | E12: =D12/B12 -> 0 | F12: =SUMIFS('Raw Data'!$E$2:$E$121,'Raw Data'!$K$2:$K$121,A12,'Raw Data'!$G$2:$G$121,"Completed") -> 1935 | G12: =IFERROR(F12/C12,0) -> 645
A13: Johar Town -> Cantt | B13: =COUNTIF('Raw Data'!$K$2:$K$121,A13) -> 3 | C13: =COUNTIFS('Raw Data'!$K$2:$K$121,A13,'Raw Data'!$G$2:$G$121,"Completed") -> 2 | D13: =COUNTIFS('Raw Data'!$K$2:$K$121,A13,'Raw Data'!$G$2:$G$121,"Cancelled") -> 1 | E13: =D13/B13 -> 0.33333333 | F13: =SUMIFS('Raw Data'!$E$2:$E$121,'Raw Data'!$K$2:$K$121,A13,'Raw Data'!$G$2:$G$121,"Completed") -> 1003 | G13: =IFERROR(F13/C13,0) -> 501.5
A14: Johar Town -> DHA | B14: =COUNTIF('Raw Data'!$K$2:$K$121,A14) -> 5 | C14: =COUNTIFS('Raw Data'!$K$2:$K$121,A14,'Raw Data'!$G$2:$G$121,"Completed") -> 4 | D14: =COUNTIFS('Raw Data'!$K$2:$K$121,A14,'Raw Data'!$G$2:$G$121,"Cancelled") -> 1 | E14: =D14/B14 -> 0.2 | F14: =SUMIFS('Raw Data'!$E$2:$E$121,'Raw Data'!$K$2:$K$121,A14,'Raw Data'!$G$2:$G$121,"Completed") -> 2747 | G14: =IFERROR(F14/C14,0) -> 686.75
A15: Johar Town -> Gulberg | B15: =COUNTIF('Raw Data'!$K$2:$K$121,A15) -> 3 | C15: =COUNTIFS('Raw Data'!$K$2:$K$121,A15,'Raw Data'!$G$2:$G$121,"Completed") -> 3 | D15: =COUNTIFS('Raw Data'!$K$2:$K$121,A15,'Raw Data'!$G$2:$G$121,"Cancelled") -> 0 | E15: =D15/B15 -> 0 | F15: =SUMIFS('Raw Data'!$E$2:$E$121,'Raw Data'!$K$2:$K$121,A15,'Raw Data'!$G$2:$G$121,"Completed") -> 1894 | G15: =IFERROR(F15/C15,0) -> 631.33333
A16: Johar Town -> Model Town | B16: =COUNTIF('Raw Data'!$K$2:$K$121,A16) -> 3 | C16: =COUNTIFS('Raw Data'!$K$2:$K$121,A16,'Raw Data'!$G$2:$G$121,"Completed") -> 1 | D16: =COUNTIFS('Raw Data'!$K$2:$K$121,A16,'Raw Data'!$G$2:$G$121,"Cancelled") -> 2 | E16: =D16/B16 -> 0.66666667 | F16: =SUMIFS('Raw Data'!$E$2:$E$121,'Raw Data'!$K$2:$K$121,A16,'Raw Data'!$G$2:$G$121,"Completed") -> 1054 | G16: =IFERROR(F16/C16,0) -> 1054
... A24: Wapda Town -> Model Town | B24: =COUNTIF('Raw Data'!$K$2:$K$121,A24) -> 3 | C24: =COUNTIFS('Raw Data'!$K$2:$K$121,A24,'Raw Data'!$G$2:$G$121,"Completed") -> 2 | D24: =COUNTIFS('Raw Data'!$K$2:$K$121,A24,'Raw Data'!$G$2:$G$121,"Cancelled") -> 1 | E24: =D24/B24 -> 0.33333333 | F24: =SUMIFS('Raw Data'!$E$2:$E$121,'Raw Data'!$K$2:$K$121,A24,'Raw Data'!$G$2:$G$121,"Completed") -> 1859 | G24: =IFERROR(F24/C24,0) -> 929.5

Sheet Payment Method
A1: Revenue & Cancellation by Payment Method
A3: Payment Method | B3: Total Rides | C3: Completed | D3: Cancelled | E3: Cancellation Rate | F3: Revenue | G3: Revenue % of Total | H3: Avg Fare (Completed)
A4: Card | B4: =COUNTIF('Raw Data'!$F$2:$F$121,A4) -> 45 | C4: =COUNTIFS('Raw Data'!$F$2:$F$121,A4,'Raw Data'!$G$2:$G$121,"Completed") -> 38 | D4: =COUNTIFS('Raw Data'!$F$2:$F$121,A4,'Raw Data'!$G$2:$G$121,"Cancelled") -> 7 | E4: =D4/B4 -> 0.15555556 | F4: =SUMIFS('Raw Data'!$E$2:$E$121,'Raw Data'!$F$2:$F$121,A4,'Raw Data'!$G$2:$G$121,"Completed") -> 26425 | G4: =F4/'KPI Summary'!$B$10 -> 0.40388525 | H4: =IFERROR(F4/C4,0) -> 695.39474
A5: Cash | B5: =COUNTIF('Raw Data'!$F$2:$F$121,A5) -> 42 | C5: =COUNTIFS('Raw Data'!$F$2:$F$121,A5,'Raw Data'!$G$2:$G$121,"Completed") -> 33 | D5: =COUNTIFS('Raw Data'!$F$2:$F$121,A5,'Raw Data'!$G$2:$G$121,"Cancelled") -> 9 | E5: =D5/B5 -> 0.21428571 | F5: =SUMIFS('Raw Data'!$E$2:$E$121,'Raw Data'!$F$2:$F$121,A5,'Raw Data'!$G$2:$G$121,"Completed") -> 21548 | G5: =F5/'KPI Summary'!$B$10 -> 0.32934415 | H5: =IFERROR(F5/C5,0) -> 652.9697
A6: Wallet | B6: =COUNTIF('Raw Data'!$F$2:$F$121,A6) -> 33 | C6: =COUNTIFS('Raw Data'!$F$2:$F$121,A6,'Raw Data'!$G$2:$G$121,"Completed") -> 25 | D6: =COUNTIFS('Raw Data'!$F$2:$F$121,A6,'Raw Data'!$G$2:$G$121,"Cancelled") -> 8 | E6: =D6/B6 -> 0.24242424 | F6: =SUMIFS('Raw Data'!$E$2:$E$121,'Raw Data'!$F$2:$F$121,A6,'Raw Data'!$G$2:$G$121,"Completed") -> 17454 | G6: =F6/'KPI Summary'!$B$10 -> 0.2667706 | H6: =IFERROR(F6/C6,0) -> 698.16

Sheet Fare Segment Analysis
A1: Fare-Tier Segmentation (proxy for customer segmentation)
A2: No customer ID exists in this dataset, so true ride-frequency segmentation is not possible. Rides are grouped into Low/Mid/High fare tiers instead - see Limitations.
A4: Fare Tier | B4: Rides | C4: % of Completed Rides | D4: Revenue | E4: % of Total Revenue | F4: Avg Fare
A5: Low | B5: =COUNTIFS('Raw Data'!$L$2:$L$121,A5,'Raw Data'!$G$2:$G$121,"Completed") -> 32 | C5: =B5/'KPI Summary'!$B$6 -> 0.33333333 | D5: =SUMIFS('Raw Data'!$E$2:$E$121,'Raw Data'!$L$2:$L$121,A5,'Raw Data'!$G$2:$G$121,"Completed") -> 11185 | E5: =D5/'KPI Summary'!$B$10 -> 0.17095389 | F5: =IFERROR(D5/B5,0) -> 349.53125
A6: Mid | B6: =COUNTIFS('Raw Data'!$L$2:$L$121,A6,'Raw Data'!$G$2:$G$121,"Completed") -> 32 | C6: =B6/'KPI Summary'!$B$6 -> 0.33333333 | D6: =SUMIFS('Raw Data'!$E$2:$E$121,'Raw Data'!$L$2:$L$121,A6,'Raw Data'!$G$2:$G$121,"Completed") -> 21582 | E6: =D6/'KPI Summary'!$B$10 -> 0.32986382 | F6: =IFERROR(D6/B6,0) -> 674.4375
A7: High | B7: =COUNTIFS('Raw Data'!$L$2:$L$121,A7,'Raw Data'!$G$2:$G$121,"Completed") -> 32 | C7: =B7/'KPI Summary'!$B$6 -> 0.33333333 | D7: =SUMIFS('Raw Data'!$E$2:$E$121,'Raw Data'!$L$2:$L$121,A7,'Raw Data'!$G$2:$G$121,"Completed") -> 32660 | E7: =D7/'KPI Summary'!$B$10 -> 0.49918229 | F7: =IFERROR(D7/B7,0) -> 1020.625

Sheet Scenario Analysis
A1: What-If Scenario: Cancellation Reduction & Fare Change
A2: Estimates only - not guaranteed outcomes. Edit the yellow input cells.
A4: Inputs (edit the yellow cells)
A5: Current Cancellation Rate | B5: ='KPI Summary'!B9 -> 0.2
A6: Target Cancellation Rate | B6: 0.15
A7: Current Average Fare | B7: ='KPI Summary'!B10/'KPI Summary'!B6 -> 681.53125
A8: Assumed Fare Increase % | B8: 0.05
A10: Scenario Outputs
A11: Total Rides (unchanged) | B11: ='KPI Summary'!B5 -> 120
A12: Additional Completed Rides (if cancellation drops to target) | B12: =ROUND(B11*(B5-B6),0) -> 6
A13: Estimated Extra Revenue from Fewer Cancellations | B13: =B12*B7 -> 4089.1875
A14: Estimated Revenue Impact of Fare Increase (existing completed rides) | B14: ='KPI Summary'!B10*B8 -> 3271.35
A15: Combined Estimated Revenue Uplift | B15: =B13+B14 -> 7360.5375
A16: Combined Uplift as % of Current Revenue | B16: =B15/'KPI Summary'!B10 -> 0.1125
A19: Assumptions: fare mix and demand pattern stay constant; 'target cancellation rate' assumes lost rides convert to completed rides at the current average fare; no cost data exists, so these are revenue (not profit) estimates.

Sheet DAX Measures
A1: DAX Measure Library
A2: Copy these into Power BI's Modeling > New Measure. They mirror the formulas validated on the sheets above.
A4: Measure Name | B4: DAX Formula
A5: Total Revenue | B5: Total Revenue = CALCULATE(SUM('Raw Data'[Fare]), 'Raw Data'[Ride Status] = "Completed")
A6: Completed Rides | B6: Completed Rides = CALCULATE(COUNTROWS('Raw Data'), 'Raw Data'[Ride Status] = "Completed")
A7: Cancelled Rides | B7: Cancelled Rides = CALCULATE(COUNTROWS('Raw Data'), 'Raw Data'[Ride Status] = "Cancelled")
A8: Total Rides | B8: Total Rides = COUNTROWS('Raw Data')
A9: Completion Rate | B9: Completion Rate = DIVIDE([Completed Rides], [Total Rides])
A10: Cancellation Rate | B10: Cancellation Rate = DIVIDE([Cancelled Rides], [Total Rides])
A11: Average Fare | B11: Average Fare = CALCULATE(AVERAGE('Raw Data'[Fare]), 'Raw Data'[Ride Status] = "Completed")
A12: Average Distance | B12: -- Not available: dataset has no distance column. Add one before implementing.
A13: Average Rating | B13: Average Rating = AVERAGE('Raw Data'[Rating])
A14: Revenue per Completed Ride | B14: Revenue per Completed Ride = DIVIDE([Total Revenue], [Completed Rides])
A15: Revenue (Previous Week) | B15: Revenue PW = CALCULATE([Total Revenue], DATEADD('Date Table'[Date], -7, DAY))
... A19: Revenue % of Total (Contribution) | B19: Revenue % of Total = DIVIDE([Total Revenue], CALCULATE([Total Revenue], ALL('Raw Data')))
